cvx/covariance/__init__.py
cvx/covariance/combination.py
cvx/covariance/ewma.py
cvx/covariance/regularization.py
cvxcovariance-0.1.9.dist-info/METADATA
cvxcovariance-0.1.9.dist-info/WHEEL
cvxcovariance-0.1.9.dist-info/licenses/LICENSE
cvxcovariance-0.1.9.dist-info/RECORD
