Metadata-Version: 2.4
Name: cvxcovariance
Version: 0.1.9
Summary: Estimating covariance matrices of financial returns
Project-URL: repository, https://github.com/cvxgrp/cov_pred_finance
Author-email: Kasper Johansson <kasper@stanford.edu>, Thomas Schmelzer <thomas.schmelzer@gmail.com>
License-File: LICENSE
Requires-Python: >=3.10
Requires-Dist: clarabel>=0.9.0
Requires-Dist: cvxpy-base>=1.6.0
Requires-Dist: numpy>=2
Requires-Dist: pandas>=2
Requires-Dist: scipy>=1.15.1
